README.rst
setup.py
jsonrpclient/__init__.py
jsonrpclient/client.py
jsonrpclient/error.py
jsonrpclient/handler.py
jsonrpclient.egg-info/PKG-INFO
jsonrpclient.egg-info/SOURCES.txt
jsonrpclient.egg-info/dependency_links.txt
jsonrpclient.egg-info/requires.txt
jsonrpclient.egg-info/top_level.txt
test/test_client.py